dikicli/__init__.py
dikicli/__main__.py
dikicli/cli.py
dikicli/core.py
dikicli/templates.py
dikicli-0.5.0.dist-info/entry_points.txt
dikicli-0.5.0.dist-info/WHEEL
dikicli-0.5.0.dist-info/METADATA
dikicli-0.5.0.dist-info/LICENSE
dikicli-0.5.0.dist-info/RECORD
