Metadata-Version: 2.1
Name: dikicli
Version: 0.5.0
Summary: Commandline interface for diki.pl polish-english dictionary
Home-page: https://github.com/silenc3r/dikicli
License: MIT
Keywords: diki,dictionary
Author: Dawid Zych
Author-email: dwd@mailo.com
Requires-Python: >=3.6,<4.0
Classifier: Development Status :: 5 - Production/Stable
Classifier: Environment :: Console
Classifier: Intended Audience :: Education
Classifier: Intended Audience :: End Users/Desktop
Classifier: License :: OSI Approved :: MIT License
Classifier: Natural Language :: Polish
Classifier: Operating System :: POSIX
Classifier: Programming Language :: Python :: 3
Classifier: Programming Language :: Python :: 3.6
Classifier: Programming Language :: Python :: 3.7
Classifier: Programming Language :: Python :: 3.8
Classifier: Programming Language :: Python :: 3.9
Classifier: Programming Language :: Python :: 3.10
Classifier: Programming Language :: Python :: 3.11
Classifier: Topic :: Education
Requires-Dist: beautifulsoup4 (>=4.0)
Requires-Dist: requests (>=2.25.1)
Project-URL: Repository, https://github.com/silenc3r/dikicli
